setup.py
pymill/__init__.py
pymill/pymill.py
pymill.egg-info/PKG-INFO
pymill.egg-info/SOURCES.txt
pymill.egg-info/dependency_links.txt
pymill.egg-info/requires.txt
pymill.egg-info/top_level.txt